animate_netcdf/__init__.py
animate_netcdf/__main__.py
animate_netcdf/core/__init__.py
animate_netcdf/core/app_controller.py
animate_netcdf/core/cli_parser.py
animate_netcdf/core/config_manager.py
animate_netcdf/core/explorer.py
animate_netcdf/core/file_manager.py
animate_netcdf/core/interactive_flow.py
animate_netcdf/core/output_manager.py
animate_netcdf/utils/__init__.py
animate_netcdf/utils/data_processing.py
animate_netcdf/utils/ffmpeg_utils.py
animate_netcdf/utils/group_extractor.py
animate_netcdf/utils/logging_utils.py
animate_netcdf/utils/netcdf_explorer.py
animate_netcdf/utils/plot_utils.py
animate_netcdf/visualizers/__init__.py
animate_netcdf/visualizers/unified_visualizer.py
animate_netcdf-1.7.2.dist-info/licenses/LICENSE
animate_netcdf-1.7.2.dist-info/METADATA
animate_netcdf-1.7.2.dist-info/WHEEL
animate_netcdf-1.7.2.dist-info/entry_points.txt
animate_netcdf-1.7.2.dist-info/top_level.txt
animate_netcdf-1.7.2.dist-info/RECORD
