Metadata-Version: 2.4
Name: animate-netcdf
Version: 1.7.2
Summary: A comprehensive tool for creating animations from NetCDF data files
Home-page: https://github.com/floriancochard/animate-netcdf
Author: Florian Cochard
Author-email: Florian Cochard <florian@weatherwise.fr>
Maintainer-email: Florian Cochard <florian@weatherwise.fr>
License: MIT License
Project-URL: Homepage, https://github.com/floriancochard/animate-netcdf
Project-URL: Repository, https://github.com/floriancochard/animate-netcdf
Project-URL: Documentation, https://github.com/floriancochard/animate-netcdf#readme
Project-URL: Issues, https://github.com/floriancochard/animate-netcdf/issues
Keywords: netcdf,animation,visualization,climate,weather,oceanography
Classifier: Development Status :: 4 - Beta
Classifier: Intended Audience :: Science/Research
Classifier: Operating System :: OS Independent
Classifier: Programming Language :: Python :: 3
Classifier: Programming Language :: Python :: 3.7
Classifier: Programming Language :: Python :: 3.8
Classifier: Programming Language :: Python :: 3.9
Classifier: Programming Language :: Python :: 3.10
Classifier: Programming Language :: Python :: 3.11
Classifier: Topic :: Scientific/Engineering :: Visualization
Classifier: Topic :: Multimedia :: Video
Requires-Python: >=3.7
License-File: LICENSE
Requires-Dist: xarray>=2023.1.0
Requires-Dist: numpy>=1.21.0
Requires-Dist: matplotlib>=3.5.0
Requires-Dist: cartopy>=0.20.0
Requires-Dist: psutil>=5.8.0
Requires-Dist: netCDF4>=1.6.0
Provides-Extra: dev
Requires-Dist: pytest>=6.0; extra == "dev"
Requires-Dist: pytest-cov>=2.0; extra == "dev"
Requires-Dist: black>=21.0; extra == "dev"
Requires-Dist: flake8>=3.8; extra == "dev"
Dynamic: author
Dynamic: home-page
Dynamic: license-file
Dynamic: requires-python
